README.md
setup.cfg
setup.py
./kabuka/kabuka
kabuka/__init__.py
kabuka/__main__.py
kabuka/kabuka.py
kabuka/test_kabuka.py
kabuka.egg-info/PKG-INFO
kabuka.egg-info/SOURCES.txt
kabuka.egg-info/dependency_links.txt
kabuka.egg-info/requires.txt
kabuka.egg-info/top_level.txt