Metadata-Version: 2.1
Name: kabuka
Version: 0.1.0
Summary: get latest stock price from Yahoo! Finance
Home-page: https://github.com/sdanaipat/kabuka
Author: Danaipat Sodkomkham
Author-email: sdanaipat@gmail.com
License: MIT
Download-URL: https://github.com/sdanaipat/kabuka/archive/v0.1.0.tar.gz
Keywords: stock price,yahoo finance,market price,get latest stock price
Platform: UNKNOWN
Classifier: Development Status :: 3 - Alpha
Classifier: Intended Audience :: Developers
Classifier: Topic :: Office/Business :: Financial
Classifier: License :: OSI Approved :: MIT License
Classifier: Programming Language :: Python :: 3.6
Classifier: Programming Language :: Python :: 3.7
Classifier: Programming Language :: Python :: 3.8
Classifier: Programming Language :: Python :: 3.9
